django_chrono/__init__.py
django_chrono/utils.py
django_chrono-0.1.2.dist-info/licenses/LICENSE
django_chrono-0.1.2.dist-info/METADATA
django_chrono-0.1.2.dist-info/WHEEL
django_chrono-0.1.2.dist-info/top_level.txt
django_chrono-0.1.2.dist-info/RECORD
