Metadata-Version: 2.4
Name: django-chrono
Version: 0.1.2
Summary: django-chrono is a helper class for date and time operations in Django projects.
Author-email: Kalinin Mitko <kalinin.mitko@gmail.com>
License: MIT License
Project-URL: Homepage, https://github.com/null-none/django-chrono
Keywords: django,hotnet,ajax
Classifier: License :: OSI Approved :: MIT License
Classifier: Programming Language :: Python
Classifier: Programming Language :: Python :: 3
Requires-Python: >=3.9
License-File: LICENSE
Provides-Extra: dev
Requires-Dist: pip-tools; extra == "dev"
Dynamic: license-file
